libbr/__init__.py
libbr/core.py
libbr/layout.py
libbr/widgets.py
libbr-0.1.3.dist-info/LICENSE
libbr-0.1.3.dist-info/METADATA
libbr-0.1.3.dist-info/WHEEL
libbr-0.1.3.dist-info/top_level.txt
libbr-0.1.3.dist-info/RECORD
