Metadata-Version: 2.1
Name: libbr
Version: 0.1.3
Summary: Uma biblioteca gráfica simples e brasileira, estilo PySimpleGUI.
Author: Renata Machado Barreto Braga
Classifier: Programming Language :: Python :: 3
Classifier: License :: OSI Approved :: MIT License
Classifier: Operating System :: OS Independent
Requires-Python: >=3.7
License-File: LICENSE
